umls_downloader/__init__.py
umls_downloader/__main__.py
umls_downloader/api.py
umls_downloader/cli.py
umls_downloader/rxnorm.py
umls_downloader/semmeddb.py
umls_downloader/snomed.py
umls_downloader/umls.py
umls_downloader/version.py
umls_downloader-0.1.3.dist-info/LICENSE
umls_downloader-0.1.3.dist-info/METADATA
umls_downloader-0.1.3.dist-info/WHEEL
umls_downloader-0.1.3.dist-info/entry_points.txt
umls_downloader-0.1.3.dist-info/top_level.txt
umls_downloader-0.1.3.dist-info/RECORD
