Metadata-Version: 2.1
Name: umls_downloader
Version: 0.1.3
Summary: Automate downloading UMLS data.
Home-page: https://github.com/cthoyt/umls_downloader
Download-URL: https://github.com/cthoyt/umls_downloader/releases
Author: Charles Tapley Hoyt
Author-email: cthoyt@gmail.com
Maintainer: Charles Tapley Hoyt
Maintainer-email: cthoyt@gmail.com
License: MIT
Project-URL: Bug Tracker, https://github.com/cthoyt/umls_downloader/issues
Project-URL: Source Code, https://github.com/cthoyt/umls_downloader
Keywords: snekpack,cookiecutter,UMLS,SNOMED-CT,RxNorm
Classifier: Development Status :: 1 - Planning
Classifier: Environment :: Console
Classifier: Intended Audience :: Developers
Classifier: License :: OSI Approved :: MIT License
Classifier: Operating System :: OS Independent
Classifier: Framework :: Pytest
Classifier: Framework :: tox
Classifier: Framework :: Sphinx
Classifier: Programming Language :: Python
Classifier: Programming Language :: Python :: 3.7
Classifier: Programming Language :: Python :: 3.8
Classifier: Programming Language :: Python :: 3.9
Classifier: Programming Language :: Python :: 3.10
Classifier: Programming Language :: Python :: 3 :: Only
Requires-Python: >=3.7
License-File: LICENSE
Requires-Dist: click
Requires-Dist: more_click
Requires-Dist: beautifulsoup4
Requires-Dist: requests
Requires-Dist: pystow
Provides-Extra: bioversions
Requires-Dist: bioversions; extra == "bioversions"
Provides-Extra: tests
Requires-Dist: pytest; extra == "tests"
Requires-Dist: coverage; extra == "tests"
Provides-Extra: docs
Requires-Dist: sphinx; extra == "docs"
Requires-Dist: sphinx-rtd-theme; extra == "docs"
Requires-Dist: sphinx-click; extra == "docs"
Requires-Dist: sphinx-autodoc-typehints; extra == "docs"
Requires-Dist: sphinx_automodapi; extra == "docs"
